better_crud/__init__.py
better_crud/_version.py
better_crud/backend.py
better_crud/config.py
better_crud/decorator.py
better_crud/depends.py
better_crud/enums.py
better_crud/exceptions.py
better_crud/factory.py
better_crud/generator.py
better_crud/helper.py
better_crud/models.py
better_crud/pagination.py
better_crud/types.py
better_crud/service/__init__.py
better_crud/service/abstract.py
better_crud/service/sqlalchemy/__init__.py
better_crud/service/sqlalchemy/helper.py
better_crud/service/sqlalchemy/service.py
better_crud-0.1.9.dist-info/licenses/LICENSE
better_crud-0.1.9.dist-info/METADATA
better_crud-0.1.9.dist-info/WHEEL
better_crud-0.1.9.dist-info/top_level.txt
better_crud-0.1.9.dist-info/RECORD
