Metadata-Version: 2.4
Name: better_crud
Version: 0.1.9
Summary: A better CRUD library for FastAPI.
Home-page: https://github.com/bigrivi/better_crud
Author: bigrivi
Author-email: sunjianghong@gmail.com
License: Apache License 2.0
Project-URL: Documentation, https://bigrivi.github.io/better_crud
Project-URL: Source Code, https://github.com/bigrivi/better_crud
Keywords: fastapi,better-crud,crud,async,sqlalchemy,pydantic
Classifier: Development Status :: 4 - Beta
Classifier: Intended Audience :: Developers
Classifier: Topic :: Software Development :: Libraries
Classifier: License :: OSI Approved :: MIT License
Classifier: Programming Language :: Python :: 3
Classifier: Programming Language :: Python :: 3.9
Classifier: Programming Language :: Python :: 3.10
Classifier: Programming Language :: Python :: 3.11
Classifier: Programming Language :: Python :: 3.12
Classifier: Operating System :: OS Independent
Classifier: Framework :: FastAPI
Classifier: Typing :: Typed
Requires-Python: >=3.9
License-File: LICENSE
Requires-Dist: fastapi>=0.111.0
Requires-Dist: sqlalchemy>=2.0.30
Requires-Dist: fastapi_pagination>=0.12.24
Requires-Dist: pydantic>=2.7.3
Dynamic: author
Dynamic: author-email
Dynamic: classifier
Dynamic: description
Dynamic: description-content-type
Dynamic: home-page
Dynamic: keywords
Dynamic: license
Dynamic: license-file
Dynamic: project-url
Dynamic: requires-dist
Dynamic: requires-python
Dynamic: summary
